csvkey/__init__.py
csvkey/connection.py
csvkey-0.0.3.dist-info/LICENSE
csvkey-0.0.3.dist-info/METADATA
csvkey-0.0.3.dist-info/WHEEL
csvkey-0.0.3.dist-info/top_level.txt
csvkey-0.0.3.dist-info/RECORD
