Metadata-Version: 2.1
Name: csvkey
Version: 0.0.3
Summary: use PRIMARY KEY and UNIQUE in CSV
Home-page: https://github.com/kittoku/csvkey
Author: KOBAYASHI Ittoku
Author-email: nono381d815@gmail.com
License: UNKNOWN
Platform: UNKNOWN
Classifier: Programming Language :: Python :: 3
Classifier: License :: OSI Approved :: MIT License
Classifier: Operating System :: OS Independent
Requires-Dist: pandas
Requires-Dist: pyyaml
